batch_executer/__init__.py
batch_executer/batch_executer.py
batch_executer/cli.py
batch_executer-0.0.1.dist-info/licenses/AUTHORS.rst
batch_executer-0.0.1.dist-info/licenses/LICENSE
batch_executer-0.0.1.dist-info/METADATA
batch_executer-0.0.1.dist-info/WHEEL
batch_executer-0.0.1.dist-info/top_level.txt
batch_executer-0.0.1.dist-info/RECORD
