Metadata-Version: 2.4
Name: batch_executer
Version: 0.0.1
Summary: A high-performance batch executor supporting async, threading, multiprocessing, and hybrid execution modes with progress bars and logging.
Author-email: Rex Wang <1073853456@qq.com>
Maintainer-email: Rex Wang <1073853456@qq.com>
License: MIT license
Project-URL: bugs, https://github.com/{{ cookiecutter.github_username }}/{{ cookiecutter.project_slug }}/issues
Project-URL: changelog, https://github.com/{{ cookiecutter.github_username }}/{{ cookiecutter.project_slug }}/blob/master/changelog.md
Project-URL: homepage, https://github.com/{{ cookiecutter.github_username }}/{{ cookiecutter.project_slug }}
License-File: LICENSE
License-File: AUTHORS.rst
Provides-Extra: dev
Requires-Dist: coverage; extra == "dev"
Requires-Dist: mypy; extra == "dev"
Requires-Dist: pytest; extra == "dev"
Requires-Dist: ruff; extra == "dev"
Dynamic: license-file
